afcharts/__init__.py
afcharts/af_colours.py
afcharts/afcharts.mplstyle
afcharts/pio_template.py
afcharts/assets/__init__.py
afcharts/config/af_colours.yaml
afcharts-1.0.0b0.dist-info/licenses/LICENSE.md
afcharts-1.0.0b0.dist-info/METADATA
afcharts-1.0.0b0.dist-info/WHEEL
afcharts-1.0.0b0.dist-info/top_level.txt
afcharts-1.0.0b0.dist-info/RECORD
