Metadata-Version: 2.4
Name: afcharts
Version: 1.0.0b0
Summary: A python package to produce charts following UK Government Analysis Function guidance
Author: Crown Copyright
Maintainer-email: Nick Henden <Nick.Henden@ukhsa.gov.uk>, Tom Farley <tom.farley@ukhsa.gov.uk>, Stelios Georgiou <Stelios.Georgiou@ukhsa.gov.uk>, Frederico Rodrigues <fred.rodrigues@defra.gov.uk>, Peter Brohan <peter.brohan@communities.gov.uk>, Fahim Hossain <fahim.hossain@ukhsa.gov.uk>
Project-URL: Homepage, https://github.com/best-practice-and-impact/afcharts-py
Project-URL: Documentation, https://best-practice-and-impact.github.io/afcharts-py/
Project-URL: Source, https://github.com/best-practice-and-impact/afcharts-py
Project-URL: Issue Tracker, https://github.com/best-practice-and-impact/afcharts-py/issues
Classifier: Programming Language :: Python :: 3
Classifier: License :: OSI Approved :: MIT License
Classifier: Operating System :: OS Independent
Classifier: Development Status :: 3 - Alpha
Requires-Python: >=3.10
License-File: LICENSE.md
Requires-Dist: matplotlib>=3.10.3
Requires-Dist: plotly>=6.1.2
Requires-Dist: typeguard>=4.4.4
Requires-Dist: PyYAML>=5.0
Dynamic: license-file
